podman/__init__.py
podman/client.py
podman/tlsconfig.py
podman/api/__init__.py
podman/api/adapter_utils.py
podman/api/cached_property.py
podman/api/client.py
podman/api/http_utils.py
podman/api/parse_utils.py
podman/api/ssh.py
podman/api/tar_utils.py
podman/api/uds.py
podman/api/version.py
podman/domain/__init__.py
podman/domain/config.py
podman/domain/containers.py
podman/domain/containers_create.py
podman/domain/containers_manager.py
podman/domain/containers_run.py
podman/domain/events.py
podman/domain/images.py
podman/domain/images_build.py
podman/domain/images_manager.py
podman/domain/ipam.py
podman/domain/manager.py
podman/domain/manifests.py
podman/domain/networks.py
podman/domain/networks_manager.py
podman/domain/pods.py
podman/domain/pods_manager.py
podman/domain/registry_data.py
podman/domain/secrets.py
podman/domain/system.py
podman/domain/volumes.py
podman/errors/__init__.py
podman/errors/exceptions.py
podman_py-3.1.2.1.dist-info/LICENSE
podman_py-3.1.2.1.dist-info/METADATA
podman_py-3.1.2.1.dist-info/WHEEL
podman_py-3.1.2.1.dist-info/top_level.txt
podman_py-3.1.2.1.dist-info/RECORD
