Metadata-Version: 2.1
Name: podman-py
Version: 3.1.2.1
Summary: Bindings for Podman RESTful API
Home-page: https://github.com/containers/podman-py
Author: Brent Baude, Jhon Honce
Author-email: jhonce@redhat.com
License: Apache-2.0
Project-URL: Bug Tracker, https://github.com/containers/podman-py/issues
Project-URL: Libpod API, https://docs.podman.io/en/latest/_static/api.html
Keywords: podman,libpod
Platform: any
Classifier: Development Status :: 3 - Alpha
Classifier: Intended Audience :: Developers
Classifier: License :: OSI Approved :: Apache Software License
Classifier: Operating System :: OS Independent
Classifier: Programming Language :: Python :: 3 :: Only
Classifier: Programming Language :: Python :: 3.6
Classifier: Programming Language :: Python :: 3.7
Classifier: Programming Language :: Python :: 3.8
Classifier: Programming Language :: Python :: 3.9
Classifier: Topic :: Software Development :: Libraries :: Python Modules
Requires-Python: >=3.6
Requires-Dist: requests (>=2.24)
Requires-Dist: toml (>=0.10.2)
Requires-Dist: urllib3 (~=1.24.2)
Requires-Dist: pyxdg (~=0.26)
